{"nodes": [{"id": "home_thinline20_pi_agent_extensions_pi_vimmode_readme_md", "label": "README.md", "file_type": "document", "source_file": "README.md", "source_location": "L1"}, {"id": "pi_vimmode_readme_pi_vimmode", "label": "pi-vimmode", "file_type": "document", "source_file": "README.md", "source_location": "L1"}, {"id": "pi_vimmode_readme_install_load", "label": "Install / load", "file_type": "document", "source_file": "README.md", "source_location": "L7"}, {"id": "pi_vimmode_readme_quick_start", "label": "Quick start", "file_type": "document", "source_file": "README.md", "source_location": "L39"}, {"id": "pi_vimmode_readme_documentation", "label": "Documentation", "file_type": "document", "source_file": "README.md", "source_location": "L57"}, {"id": "pi_vimmode_readme_common_configuration", "label": "Common configuration", "file_type": "document", "source_file": "README.md", "source_location": "L67"}, {"id": "pi_vimmode_readme_recover_or_disable", "label": "Recover or disable", "file_type": "document", "source_file": "README.md", "source_location": "L104"}, {"id": "pi_vimmode_readme_architecture", "label": "Architecture", "file_type": "document", "source_file": "README.md", "source_location": "L116"}, {"id": "pi_vimmode_readme_project_docs", "label": "Project docs", "file_type": "document", "source_file": "README.md", "source_location": "L128"}, {"id": "pi_vimmode_readme_validate", "label": "Validate", "file_type": "document", "source_file": "README.md", "source_location": "L137"}], "edges": [{"source": "home_thinline20_pi_agent_extensions_pi_vimmode_readme_md", "target": "pi_vimmode_readme_pi_vimmode", "relation": "contains", "confidence": "EXTRACTED", "source_file": "README.md", "source_location": "L1", "weight": 1.0}, {"source": "pi_vimmode_readme_pi_vimmode", "target": "pi_vimmode_readme_install_load", "relation": "contains", "confidence": "EXTRACTED", "source_file": "README.md", "source_location": "L7", "weight": 1.0}, {"source": "pi_vimmode_readme_pi_vimmode", "target": "pi_vimmode_readme_quick_start", "relation": "contains", "confidence": "EXTRACTED", "source_file": "README.md", "source_location": "L39", "weight": 1.0}, {"source": "pi_vimmode_readme_pi_vimmode", "target": "pi_vimmode_readme_documentation", "relation": "contains", "confidence": "EXTRACTED", "source_file": "README.md", "source_location": "L57", "weight": 1.0}, {"source": "pi_vimmode_readme_pi_vimmode", "target": "pi_vimmode_readme_common_configuration", "relation": "contains", "confidence": "EXTRACTED", "source_file": "README.md", "source_location": "L67", "weight": 1.0}, {"source": "pi_vimmode_readme_pi_vimmode", "target": "pi_vimmode_readme_recover_or_disable", "relation": "contains", "confidence": "EXTRACTED", "source_file": "README.md", "source_location": "L104", "weight": 1.0}, {"source": "pi_vimmode_readme_pi_vimmode", "target": "pi_vimmode_readme_architecture", "relation": "contains", "confidence": "EXTRACTED", "source_file": "README.md", "source_location": "L116", "weight": 1.0}, {"source": "pi_vimmode_readme_pi_vimmode", "target": "pi_vimmode_readme_project_docs", "relation": "contains", "confidence": "EXTRACTED", "source_file": "README.md", "source_location": "L128", "weight": 1.0}, {"source": "pi_vimmode_readme_pi_vimmode", "target": "pi_vimmode_readme_validate", "relation": "contains", "confidence": "EXTRACTED", "source_file": "README.md", "source_location": "L137", "weight": 1.0}], "input_tokens": 0, "output_tokens": 0}